mistree/__init__.py
mistree/coords/__init__.py
mistree/coords/coordinate_utility.py
mistree/levy_flight/__init__.py
mistree/levy_flight/levy_flight.py
mistree/levy_flight/utility_random_walk.py
mistree/mst/__init__.py
mistree/mst/branches.py
mistree/mst/construct.py
mistree/mst/density.py
mistree/mst/get_mst_class.py
mistree/mst/graph.py
mistree/mst/hist_mst.py
mistree/mst/partition.py
mistree/mst/plot_mst.py
mistree/mst/scale_cut.py
mistree/mst/stats.py
mistree/mst/tomo.py
mistree/mst/utility_density.py
mistree/mst/utility_mst.py
mistree-2.0.0.dist-info/LICENSE.txt
mistree-2.0.0.dist-info/METADATA
mistree-2.0.0.dist-info/WHEEL
mistree-2.0.0.dist-info/top_level.txt
mistree-2.0.0.dist-info/RECORD
